django_keycloak_lma/__init__.py
django_keycloak_lma/app_settings.py
django_keycloak_lma/apps.py
django_keycloak_lma/asgi.py
django_keycloak_lma/factories.py
django_keycloak_lma/hashers.py
django_keycloak_lma/middleware.py
django_keycloak_lma/models.py
django_keycloak_lma/remote_user.py
django_keycloak_lma/response.py
django_keycloak_lma/serializers.py
django_keycloak_lma/settings.py
django_keycloak_lma/urls.py
django_keycloak_lma/views.py
django_keycloak_lma/wsgi.py
django_keycloak_lma/admin/__init__.py
django_keycloak_lma/admin/realm.py
django_keycloak_lma/admin/server.py
django_keycloak_lma/auth/__init__.py
django_keycloak_lma/auth/backends.py
django_keycloak_lma/auth/permissions.py
django_keycloak_lma/management/__init__.py
django_keycloak_lma/management/commands/__init__.py
django_keycloak_lma/management/commands/keycloak_add_user.py
django_keycloak_lma/management/commands/keycloak_refresh_realm.py
django_keycloak_lma/management/commands/keycloak_sync_resources.py
django_keycloak_lma/migrations/0001_initial.py
django_keycloak_lma/migrations/0002_auto_20180322_2059.py
django_keycloak_lma/migrations/0003_auto_20190204_1949.py
django_keycloak_lma/migrations/0004_client_service_account_profile.py
django_keycloak_lma/migrations/0005_auto_20190219_2002.py
django_keycloak_lma/migrations/0006_remove_client_service_account.py
django_keycloak_lma/migrations/0007_alter_client_id_alter_exchangedtoken_id_and_more.py
django_keycloak_lma/migrations/__init__.py
django_keycloak_lma/services/__init__.py
django_keycloak_lma/services/client.py
django_keycloak_lma/services/exceptions.py
django_keycloak_lma/services/messages.py
django_keycloak_lma/services/oidc_profile.py
django_keycloak_lma/services/permissions.py
django_keycloak_lma/services/realm.py
django_keycloak_lma/services/remote_client.py
django_keycloak_lma/services/uma.py
django_keycloak_lma/services/users.py
django_keycloak_lma/tests/__init__.py
django_keycloak_lma/tests/mixins.py
django_keycloak_lma/tests/settings.py
django_keycloak_lma-1.3.6.dist-info/METADATA
django_keycloak_lma-1.3.6.dist-info/WHEEL
django_keycloak_lma-1.3.6.dist-info/top_level.txt
django_keycloak_lma-1.3.6.dist-info/RECORD
