Metadata-Version: 2.1
Name: django_keycloak_lma
Version: 1.3.6
Summary: Modified version of the package django_keycloak (0.1.1)
Author: Vyacheslav Konovalov
Requires-Dist: djangorestframework
Requires-Dist: python-keycloak-client-pkg
